<?xml version="1.0" encoding="utf-8"?>
<annotation>
	<folder>instances_train_xml</folder>
	<filename>120.jpg</filename>
	<size>
		<width>3840</width>
		<height>2160</height>
	</size>
	
    <object>
		<pose>Unspecified</pose>
		<truncated>0</truncated>
		<difficult>0</difficult>

		<name>echinus</name>
		<bndbox>
			<xmin>607</xmin>
			<ymin>306</ymin>
			<xmax>787</xmax>
			<ymax>459</ymax>
		</bndbox>
	</object>
	
    <object>
		<pose>Unspecified</pose>
		<truncated>0</truncated>
		<difficult>0</difficult>

		<name>echinus</name>
		<bndbox>
			<xmin>348</xmin>
			<ymin>176</ymin>
			<xmax>536</xmax>
			<ymax>334</ymax>
		</bndbox>
	</object>
	
    <object>
		<pose>Unspecified</pose>
		<truncated>0</truncated>
		<difficult>0</difficult>

		<name>echinus</name>
		<bndbox>
			<xmin>2232</xmin>
			<ymin>1667</ymin>
			<xmax>2488</xmax>
			<ymax>1957</ymax>
		</bndbox>
	</object>
	
    <object>
		<pose>Unspecified</pose>
		<truncated>0</truncated>
		<difficult>0</difficult>

		<name>echinus</name>
		<bndbox>
			<xmin>1783</xmin>
			<ymin>835</ymin>
			<xmax>1904</xmax>
			<ymax>950</ymax>
		</bndbox>
	</object>
	
    <object>
		<pose>Unspecified</pose>
		<truncated>0</truncated>
		<difficult>0</difficult>

		<name>echinus</name>
		<bndbox>
			<xmin>15</xmin>
			<ymin>5</ymin>
			<xmax>286</xmax>
			<ymax>190</ymax>
		</bndbox>
	</object>
	
    <object>
		<pose>Unspecified</pose>
		<truncated>0</truncated>
		<difficult>0</difficult>

		<name>echinus</name>
		<bndbox>
			<xmin>881</xmin>
			<ymin>324</ymin>
			<xmax>993</xmax>
			<ymax>425</ymax>
		</bndbox>
	</object>
	
    <object>
		<pose>Unspecified</pose>
		<truncated>0</truncated>
		<difficult>0</difficult>

		<name>echinus</name>
		<bndbox>
			<xmin>728</xmin>
			<ymin>165</ymin>
			<xmax>844</xmax>
			<ymax>272</ymax>
		</bndbox>
	</object>
	
    <object>
		<pose>Unspecified</pose>
		<truncated>0</truncated>
		<difficult>0</difficult>

		<name>echinus</name>
		<bndbox>
			<xmin>895</xmin>
			<ymin>438</ymin>
			<xmax>1008</xmax>
			<ymax>545</ymax>
		</bndbox>
	</object>
	
    <object>
		<pose>Unspecified</pose>
		<truncated>0</truncated>
		<difficult>0</difficult>

		<name>echinus</name>
		<bndbox>
			<xmin>944</xmin>
			<ymin>636</ymin>
			<xmax>1070</xmax>
			<ymax>766</ymax>
		</bndbox>
	</object>
	
    <object>
		<pose>Unspecified</pose>
		<truncated>0</truncated>
		<difficult>0</difficult>

		<name>echinus</name>
		<bndbox>
			<xmin>3740</xmin>
			<ymin>1129</ymin>
			<xmax>3840</xmax>
			<ymax>1231</ymax>
		</bndbox>
	</object>
	
    <object>
		<pose>Unspecified</pose>
		<truncated>0</truncated>
		<difficult>0</difficult>

		<name>starfish</name>
		<bndbox>
			<xmin>3092</xmin>
			<ymin>1151</ymin>
			<xmax>3285</xmax>
			<ymax>1278</ymax>
		</bndbox>
	</object>
</annotation>
