<?xml version="1.0" encoding="utf-8"?>
<annotation>
	<folder>instances_train_xml</folder>
	<filename>1515.jpg</filename>
	<size>
		<width>3840</width>
		<height>2160</height>
	</size>
	
    <object>
		<pose>Unspecified</pose>
		<truncated>0</truncated>
		<difficult>0</difficult>

		<name>echinus</name>
		<bndbox>
			<xmin>3093</xmin>
			<ymin>1221</ymin>
			<xmax>3189</xmax>
			<ymax>1320</ymax>
		</bndbox>
	</object>
	
    <object>
		<pose>Unspecified</pose>
		<truncated>0</truncated>
		<difficult>0</difficult>

		<name>echinus</name>
		<bndbox>
			<xmin>2817</xmin>
			<ymin>1349</ymin>
			<xmax>2956</xmax>
			<ymax>1461</ymax>
		</bndbox>
	</object>
	
    <object>
		<pose>Unspecified</pose>
		<truncated>0</truncated>
		<difficult>0</difficult>

		<name>echinus</name>
		<bndbox>
			<xmin>3429</xmin>
			<ymin>1581</ymin>
			<xmax>3748</xmax>
			<ymax>1858</ymax>
		</bndbox>
	</object>
	
    <object>
		<pose>Unspecified</pose>
		<truncated>0</truncated>
		<difficult>0</difficult>

		<name>echinus</name>
		<bndbox>
			<xmin>1870</xmin>
			<ymin>1711</ymin>
			<xmax>1971</xmax>
			<ymax>1817</ymax>
		</bndbox>
	</object>
	
    <object>
		<pose>Unspecified</pose>
		<truncated>0</truncated>
		<difficult>0</difficult>

		<name>starfish</name>
		<bndbox>
			<xmin>2686</xmin>
			<ymin>1978</ymin>
			<xmax>2864</xmax>
			<ymax>2161</ymax>
		</bndbox>
	</object>
	
    <object>
		<pose>Unspecified</pose>
		<truncated>0</truncated>
		<difficult>0</difficult>

		<name>echinus</name>
		<bndbox>
			<xmin>1201</xmin>
			<ymin>1863</ymin>
			<xmax>1302</xmax>
			<ymax>1969</ymax>
		</bndbox>
	</object>
	
    <object>
		<pose>Unspecified</pose>
		<truncated>0</truncated>
		<difficult>0</difficult>

		<name>echinus</name>
		<bndbox>
			<xmin>1056</xmin>
			<ymin>1828</ymin>
			<xmax>1157</xmax>
			<ymax>1934</ymax>
		</bndbox>
	</object>
	
    <object>
		<pose>Unspecified</pose>
		<truncated>0</truncated>
		<difficult>0</difficult>

		<name>echinus</name>
		<bndbox>
			<xmin>1089</xmin>
			<ymin>1956</ymin>
			<xmax>1190</xmax>
			<ymax>2062</ymax>
		</bndbox>
	</object>
</annotation>
