<?xml version="1.0" encoding="utf-8"?>
<annotation>
	<folder>instances_train_xml</folder>
	<filename>1531.jpg</filename>
	<size>
		<width>3840</width>
		<height>2160</height>
	</size>
	
    <object>
		<pose>Unspecified</pose>
		<truncated>0</truncated>
		<difficult>0</difficult>

		<name>echinus</name>
		<bndbox>
			<xmin>2725</xmin>
			<ymin>7</ymin>
			<xmax>2937</xmax>
			<ymax>164</ymax>
		</bndbox>
	</object>
	
    <object>
		<pose>Unspecified</pose>
		<truncated>0</truncated>
		<difficult>0</difficult>

		<name>echinus</name>
		<bndbox>
			<xmin>907</xmin>
			<ymin>891</ymin>
			<xmax>1134</xmax>
			<ymax>1070</ymax>
		</bndbox>
	</object>
	
    <object>
		<pose>Unspecified</pose>
		<truncated>0</truncated>
		<difficult>0</difficult>

		<name>echinus</name>
		<bndbox>
			<xmin>2082</xmin>
			<ymin>192</ymin>
			<xmax>2274</xmax>
			<ymax>416</ymax>
		</bndbox>
	</object>
	
    <object>
		<pose>Unspecified</pose>
		<truncated>0</truncated>
		<difficult>0</difficult>

		<name>echinus</name>
		<bndbox>
			<xmin>2963</xmin>
			<ymin>648</ymin>
			<xmax>3265</xmax>
			<ymax>887</ymax>
		</bndbox>
	</object>
	
    <object>
		<pose>Unspecified</pose>
		<truncated>0</truncated>
		<difficult>0</difficult>

		<name>echinus</name>
		<bndbox>
			<xmin>1769</xmin>
			<ymin>4</ymin>
			<xmax>1967</xmax>
			<ymax>196</ymax>
		</bndbox>
	</object>
	
    <object>
		<pose>Unspecified</pose>
		<truncated>0</truncated>
		<difficult>0</difficult>

		<name>echinus</name>
		<bndbox>
			<xmin>965</xmin>
			<ymin>3</ymin>
			<xmax>1232</xmax>
			<ymax>148</ymax>
		</bndbox>
	</object>
	
    <object>
		<pose>Unspecified</pose>
		<truncated>0</truncated>
		<difficult>0</difficult>

		<name>echinus</name>
		<bndbox>
			<xmin>1600</xmin>
			<ymin>1982</ymin>
			<xmax>1914</xmax>
			<ymax>2155</ymax>
		</bndbox>
	</object>
	
    <object>
		<pose>Unspecified</pose>
		<truncated>0</truncated>
		<difficult>0</difficult>

		<name>echinus</name>
		<bndbox>
			<xmin>635</xmin>
			<ymin>753</ymin>
			<xmax>896</xmax>
			<ymax>956</ymax>
		</bndbox>
	</object>
	
    <object>
		<pose>Unspecified</pose>
		<truncated>0</truncated>
		<difficult>0</difficult>

		<name>echinus</name>
		<bndbox>
			<xmin>173</xmin>
			<ymin>562</ymin>
			<xmax>444</xmax>
			<ymax>807</ymax>
		</bndbox>
	</object>
	
    <object>
		<pose>Unspecified</pose>
		<truncated>0</truncated>
		<difficult>0</difficult>

		<name>echinus</name>
		<bndbox>
			<xmin>803</xmin>
			<ymin>353</ymin>
			<xmax>1035</xmax>
			<ymax>604</ymax>
		</bndbox>
	</object>
	
    <object>
		<pose>Unspecified</pose>
		<truncated>0</truncated>
		<difficult>0</difficult>

		<name>starfish</name>
		<bndbox>
			<xmin>2175</xmin>
			<ymin>19</ymin>
			<xmax>2308</xmax>
			<ymax>240</ymax>
		</bndbox>
	</object>
	
    <object>
		<pose>Unspecified</pose>
		<truncated>0</truncated>
		<difficult>0</difficult>

		<name>starfish</name>
		<bndbox>
			<xmin>1948</xmin>
			<ymin>324</ymin>
			<xmax>2119</xmax>
			<ymax>532</ymax>
		</bndbox>
	</object>
	
    <object>
		<pose>Unspecified</pose>
		<truncated>0</truncated>
		<difficult>0</difficult>

		<name>echinus</name>
		<bndbox>
			<xmin>569</xmin>
			<ymin>1</ymin>
			<xmax>748</xmax>
			<ymax>158</ymax>
		</bndbox>
	</object>
	
    <object>
		<pose>Unspecified</pose>
		<truncated>0</truncated>
		<difficult>0</difficult>

		<name>starfish</name>
		<bndbox>
			<xmin>2164</xmin>
			<ymin>635</ymin>
			<xmax>2325</xmax>
			<ymax>743</ymax>
		</bndbox>
	</object>
</annotation>
