<?xml version="1.0" encoding="utf-8"?>
<annotation>
	<folder>instances_train_xml</folder>
	<filename>1550.jpg</filename>
	<size>
		<width>3840</width>
		<height>2160</height>
	</size>
	
    <object>
		<pose>Unspecified</pose>
		<truncated>0</truncated>
		<difficult>0</difficult>

		<name>echinus</name>
		<bndbox>
			<xmin>736</xmin>
			<ymin>967</ymin>
			<xmax>849</xmax>
			<ymax>1074</ymax>
		</bndbox>
	</object>
	
    <object>
		<pose>Unspecified</pose>
		<truncated>0</truncated>
		<difficult>0</difficult>

		<name>echinus</name>
		<bndbox>
			<xmin>1097</xmin>
			<ymin>970</ymin>
			<xmax>1218</xmax>
			<ymax>1085</ymax>
		</bndbox>
	</object>
	
    <object>
		<pose>Unspecified</pose>
		<truncated>0</truncated>
		<difficult>0</difficult>

		<name>echinus</name>
		<bndbox>
			<xmin>2300</xmin>
			<ymin>1702</ymin>
			<xmax>2475</xmax>
			<ymax>1875</ymax>
		</bndbox>
	</object>
</annotation>
