<?xml version="1.0" encoding="utf-8"?>
<annotation>
	<folder>instances_train_xml</folder>
	<filename>1592.jpg</filename>
	<size>
		<width>720</width>
		<height>405</height>
	</size>
	
    <object>
		<pose>Unspecified</pose>
		<truncated>0</truncated>
		<difficult>0</difficult>

		<name>echinus</name>
		<bndbox>
			<xmin>38</xmin>
			<ymin>221</ymin>
			<xmax>102</xmax>
			<ymax>270</ymax>
		</bndbox>
	</object>
	
    <object>
		<pose>Unspecified</pose>
		<truncated>0</truncated>
		<difficult>0</difficult>

		<name>echinus</name>
		<bndbox>
			<xmin>265</xmin>
			<ymin>251</ymin>
			<xmax>320</xmax>
			<ymax>299</ymax>
		</bndbox>
	</object>
	
    <object>
		<pose>Unspecified</pose>
		<truncated>0</truncated>
		<difficult>0</difficult>

		<name>echinus</name>
		<bndbox>
			<xmin>433</xmin>
			<ymin>158</ymin>
			<xmax>480</xmax>
			<ymax>200</ymax>
		</bndbox>
	</object>
</annotation>
