<?xml version="1.0" encoding="utf-8"?>
<annotation>
	<folder>instances_train_xml</folder>
	<filename>1936.jpg</filename>
	<size>
		<width>3840</width>
		<height>2160</height>
	</size>
	
    <object>
		<pose>Unspecified</pose>
		<truncated>0</truncated>
		<difficult>0</difficult>

		<name>echinus</name>
		<bndbox>
			<xmin>2059</xmin>
			<ymin>819</ymin>
			<xmax>2236</xmax>
			<ymax>1000</ymax>
		</bndbox>
	</object>
	
    <object>
		<pose>Unspecified</pose>
		<truncated>0</truncated>
		<difficult>0</difficult>

		<name>echinus</name>
		<bndbox>
			<xmin>3492</xmin>
			<ymin>858</ymin>
			<xmax>3776</xmax>
			<ymax>1094</ymax>
		</bndbox>
	</object>
	
    <object>
		<pose>Unspecified</pose>
		<truncated>0</truncated>
		<difficult>0</difficult>

		<name>echinus</name>
		<bndbox>
			<xmin>2449</xmin>
			<ymin>1217</ymin>
			<xmax>2622</xmax>
			<ymax>1373</ymax>
		</bndbox>
	</object>
	
    <object>
		<pose>Unspecified</pose>
		<truncated>0</truncated>
		<difficult>0</difficult>

		<name>echinus</name>
		<bndbox>
			<xmin>1201</xmin>
			<ymin>1348</ymin>
			<xmax>1374</xmax>
			<ymax>1522</ymax>
		</bndbox>
	</object>
	
    <object>
		<pose>Unspecified</pose>
		<truncated>0</truncated>
		<difficult>0</difficult>

		<name>echinus</name>
		<bndbox>
			<xmin>2536</xmin>
			<ymin>1972</ymin>
			<xmax>2837</xmax>
			<ymax>2161</ymax>
		</bndbox>
	</object>
	
    <object>
		<pose>Unspecified</pose>
		<truncated>0</truncated>
		<difficult>0</difficult>

		<name>echinus</name>
		<bndbox>
			<xmin>2525</xmin>
			<ymin>149</ymin>
			<xmax>2676</xmax>
			<ymax>315</ymax>
		</bndbox>
	</object>
	
    <object>
		<pose>Unspecified</pose>
		<truncated>0</truncated>
		<difficult>0</difficult>

		<name>echinus</name>
		<bndbox>
			<xmin>1642</xmin>
			<ymin>410</ymin>
			<xmax>1797</xmax>
			<ymax>568</ymax>
		</bndbox>
	</object>
	
    <object>
		<pose>Unspecified</pose>
		<truncated>0</truncated>
		<difficult>0</difficult>

		<name>echinus</name>
		<bndbox>
			<xmin>2313</xmin>
			<ymin>1463</ymin>
			<xmax>2511</xmax>
			<ymax>1633</ymax>
		</bndbox>
	</object>
	
    <object>
		<pose>Unspecified</pose>
		<truncated>0</truncated>
		<difficult>0</difficult>

		<name>echinus</name>
		<bndbox>
			<xmin>1014</xmin>
			<ymin>892</ymin>
			<xmax>1111</xmax>
			<ymax>998</ymax>
		</bndbox>
	</object>
	
    <object>
		<pose>Unspecified</pose>
		<truncated>0</truncated>
		<difficult>0</difficult>

		<name>echinus</name>
		<bndbox>
			<xmin>839</xmin>
			<ymin>1037</ymin>
			<xmax>919</xmax>
			<ymax>1125</ymax>
		</bndbox>
	</object>
	
    <object>
		<pose>Unspecified</pose>
		<truncated>0</truncated>
		<difficult>0</difficult>

		<name>starfish</name>
		<bndbox>
			<xmin>1259</xmin>
			<ymin>1713</ymin>
			<xmax>1534</xmax>
			<ymax>1897</ymax>
		</bndbox>
	</object>
	
    <object>
		<pose>Unspecified</pose>
		<truncated>0</truncated>
		<difficult>0</difficult>

		<name>starfish</name>
		<bndbox>
			<xmin>760</xmin>
			<ymin>1688</ymin>
			<xmax>930</xmax>
			<ymax>1827</ymax>
		</bndbox>
	</object>
	
    <object>
		<pose>Unspecified</pose>
		<truncated>0</truncated>
		<difficult>0</difficult>

		<name>starfish</name>
		<bndbox>
			<xmin>3491</xmin>
			<ymin>1572</ymin>
			<xmax>3772</xmax>
			<ymax>1819</ymax>
		</bndbox>
	</object>
	
    <object>
		<pose>Unspecified</pose>
		<truncated>0</truncated>
		<difficult>0</difficult>

		<name>echinus</name>
		<bndbox>
			<xmin>1788</xmin>
			<ymin>59</ymin>
			<xmax>1860</xmax>
			<ymax>122</ymax>
		</bndbox>
	</object>
	
    <object>
		<pose>Unspecified</pose>
		<truncated>0</truncated>
		<difficult>0</difficult>

		<name>echinus</name>
		<bndbox>
			<xmin>1441</xmin>
			<ymin>403</ymin>
			<xmax>1504</xmax>
			<ymax>463</ymax>
		</bndbox>
	</object>
	
    <object>
		<pose>Unspecified</pose>
		<truncated>0</truncated>
		<difficult>0</difficult>

		<name>echinus</name>
		<bndbox>
			<xmin>1167</xmin>
			<ymin>631</ymin>
			<xmax>1224</xmax>
			<ymax>696</ymax>
		</bndbox>
	</object>
</annotation>
