<?xml version="1.0" encoding="utf-8"?>
<annotation>
	<folder>instances_train_xml</folder>
	<filename>2110.jpg</filename>
	<size>
		<width>3840</width>
		<height>2160</height>
	</size>
	
    <object>
		<pose>Unspecified</pose>
		<truncated>0</truncated>
		<difficult>0</difficult>

		<name>echinus</name>
		<bndbox>
			<xmin>702</xmin>
			<ymin>93</ymin>
			<xmax>805</xmax>
			<ymax>188</ymax>
		</bndbox>
	</object>
	
    <object>
		<pose>Unspecified</pose>
		<truncated>0</truncated>
		<difficult>0</difficult>

		<name>echinus</name>
		<bndbox>
			<xmin>1297</xmin>
			<ymin>193</ymin>
			<xmax>1432</xmax>
			<ymax>339</ymax>
		</bndbox>
	</object>
	
    <object>
		<pose>Unspecified</pose>
		<truncated>0</truncated>
		<difficult>0</difficult>

		<name>scallop</name>
		<bndbox>
			<xmin>1767</xmin>
			<ymin>1750</ymin>
			<xmax>1924</xmax>
			<ymax>1907</ymax>
		</bndbox>
	</object>
	
    <object>
		<pose>Unspecified</pose>
		<truncated>0</truncated>
		<difficult>0</difficult>

		<name>echinus</name>
		<bndbox>
			<xmin>654</xmin>
			<ymin>642</ymin>
			<xmax>802</xmax>
			<ymax>766</ymax>
		</bndbox>
	</object>
	
    <object>
		<pose>Unspecified</pose>
		<truncated>0</truncated>
		<difficult>0</difficult>

		<name>echinus</name>
		<bndbox>
			<xmin>2264</xmin>
			<ymin>212</ymin>
			<xmax>2340</xmax>
			<ymax>296</ymax>
		</bndbox>
	</object>
</annotation>
