<?xml version="1.0" encoding="utf-8"?>
<annotation>
	<folder>instances_train_xml</folder>
	<filename>248.jpg</filename>
	<size>
		<width>720</width>
		<height>405</height>
	</size>
	
    <object>
		<pose>Unspecified</pose>
		<truncated>0</truncated>
		<difficult>0</difficult>

		<name>holothurian</name>
		<bndbox>
			<xmin>105</xmin>
			<ymin>274</ymin>
			<xmax>185</xmax>
			<ymax>340</ymax>
		</bndbox>
	</object>
	
    <object>
		<pose>Unspecified</pose>
		<truncated>0</truncated>
		<difficult>0</difficult>

		<name>holothurian</name>
		<bndbox>
			<xmin>146</xmin>
			<ymin>158</ymin>
			<xmax>233</xmax>
			<ymax>226</ymax>
		</bndbox>
	</object>
	
    <object>
		<pose>Unspecified</pose>
		<truncated>0</truncated>
		<difficult>0</difficult>

		<name>echinus</name>
		<bndbox>
			<xmin>300</xmin>
			<ymin>243</ymin>
			<xmax>400</xmax>
			<ymax>347</ymax>
		</bndbox>
	</object>
	
    <object>
		<pose>Unspecified</pose>
		<truncated>0</truncated>
		<difficult>0</difficult>

		<name>starfish</name>
		<bndbox>
			<xmin>252</xmin>
			<ymin>128</ymin>
			<xmax>297</xmax>
			<ymax>180</ymax>
		</bndbox>
	</object>
</annotation>
