<?xml version="1.0" encoding="utf-8"?>
<annotation>
	<folder>instances_train_xml</folder>
	<filename>4158.jpg</filename>
	<size>
		<width>3840</width>
		<height>2160</height>
	</size>
	
    <object>
		<pose>Unspecified</pose>
		<truncated>0</truncated>
		<difficult>0</difficult>

		<name>holothurian</name>
		<bndbox>
			<xmin>1620</xmin>
			<ymin>1808</ymin>
			<xmax>2097</xmax>
			<ymax>2008</ymax>
		</bndbox>
	</object>
	
    <object>
		<pose>Unspecified</pose>
		<truncated>0</truncated>
		<difficult>0</difficult>

		<name>echinus</name>
		<bndbox>
			<xmin>1486</xmin>
			<ymin>1389</ymin>
			<xmax>1923</xmax>
			<ymax>1877</ymax>
		</bndbox>
	</object>
	
    <object>
		<pose>Unspecified</pose>
		<truncated>0</truncated>
		<difficult>0</difficult>

		<name>echinus</name>
		<bndbox>
			<xmin>2</xmin>
			<ymin>892</ymin>
			<xmax>185</xmax>
			<ymax>1136</ymax>
		</bndbox>
	</object>
</annotation>
