<?xml version="1.0" encoding="utf-8"?>
<annotation>
	<folder>instances_train_xml</folder>
	<filename>508.jpg</filename>
	<size>
		<width>1920</width>
		<height>1080</height>
	</size>
	
    <object>
		<pose>Unspecified</pose>
		<truncated>0</truncated>
		<difficult>0</difficult>

		<name>holothurian</name>
		<bndbox>
			<xmin>1234</xmin>
			<ymin>561</ymin>
			<xmax>1355</xmax>
			<ymax>685</ymax>
		</bndbox>
	</object>
	
    <object>
		<pose>Unspecified</pose>
		<truncated>0</truncated>
		<difficult>0</difficult>

		<name>holothurian</name>
		<bndbox>
			<xmin>1275</xmin>
			<ymin>420</ymin>
			<xmax>1416</xmax>
			<ymax>487</ymax>
		</bndbox>
	</object>
	
    <object>
		<pose>Unspecified</pose>
		<truncated>0</truncated>
		<difficult>0</difficult>

		<name>holothurian</name>
		<bndbox>
			<xmin>308</xmin>
			<ymin>983</ymin>
			<xmax>430</xmax>
			<ymax>1073</ymax>
		</bndbox>
	</object>
	
    <object>
		<pose>Unspecified</pose>
		<truncated>0</truncated>
		<difficult>0</difficult>

		<name>echinus</name>
		<bndbox>
			<xmin>924</xmin>
			<ymin>646</ymin>
			<xmax>1016</xmax>
			<ymax>728</ymax>
		</bndbox>
	</object>
	
    <object>
		<pose>Unspecified</pose>
		<truncated>0</truncated>
		<difficult>0</difficult>

		<name>echinus</name>
		<bndbox>
			<xmin>1002</xmin>
			<ymin>418</ymin>
			<xmax>1088</xmax>
			<ymax>491</ymax>
		</bndbox>
	</object>
	
    <object>
		<pose>Unspecified</pose>
		<truncated>0</truncated>
		<difficult>0</difficult>

		<name>echinus</name>
		<bndbox>
			<xmin>682</xmin>
			<ymin>628</ymin>
			<xmax>761</xmax>
			<ymax>695</ymax>
		</bndbox>
	</object>
	
    <object>
		<pose>Unspecified</pose>
		<truncated>0</truncated>
		<difficult>0</difficult>

		<name>echinus</name>
		<bndbox>
			<xmin>1828</xmin>
			<ymin>629</ymin>
			<xmax>1918</xmax>
			<ymax>713</ymax>
		</bndbox>
	</object>
	
    <object>
		<pose>Unspecified</pose>
		<truncated>0</truncated>
		<difficult>0</difficult>

		<name>echinus</name>
		<bndbox>
			<xmin>475</xmin>
			<ymin>471</ymin>
			<xmax>554</xmax>
			<ymax>538</ymax>
		</bndbox>
	</object>
	
    <object>
		<pose>Unspecified</pose>
		<truncated>0</truncated>
		<difficult>0</difficult>

		<name>echinus</name>
		<bndbox>
			<xmin>971</xmin>
			<ymin>323</ymin>
			<xmax>1035</xmax>
			<ymax>382</ymax>
		</bndbox>
	</object>
	
    <object>
		<pose>Unspecified</pose>
		<truncated>0</truncated>
		<difficult>0</difficult>

		<name>echinus</name>
		<bndbox>
			<xmin>1801</xmin>
			<ymin>527</ymin>
			<xmax>1876</xmax>
			<ymax>588</ymax>
		</bndbox>
	</object>
	
    <object>
		<pose>Unspecified</pose>
		<truncated>0</truncated>
		<difficult>0</difficult>

		<name>echinus</name>
		<bndbox>
			<xmin>567</xmin>
			<ymin>328</ymin>
			<xmax>641</xmax>
			<ymax>392</ymax>
		</bndbox>
	</object>
	
    <object>
		<pose>Unspecified</pose>
		<truncated>0</truncated>
		<difficult>0</difficult>

		<name>echinus</name>
		<bndbox>
			<xmin>575</xmin>
			<ymin>422</ymin>
			<xmax>648</xmax>
			<ymax>503</ymax>
		</bndbox>
	</object>
	
    <object>
		<pose>Unspecified</pose>
		<truncated>0</truncated>
		<difficult>0</difficult>

		<name>echinus</name>
		<bndbox>
			<xmin>838</xmin>
			<ymin>362</ymin>
			<xmax>891</xmax>
			<ymax>413</ymax>
		</bndbox>
	</object>
	
    <object>
		<pose>Unspecified</pose>
		<truncated>0</truncated>
		<difficult>0</difficult>

		<name>echinus</name>
		<bndbox>
			<xmin>413</xmin>
			<ymin>695</ymin>
			<xmax>474</xmax>
			<ymax>757</ymax>
		</bndbox>
	</object>
	
    <object>
		<pose>Unspecified</pose>
		<truncated>0</truncated>
		<difficult>0</difficult>

		<name>echinus</name>
		<bndbox>
			<xmin>433</xmin>
			<ymin>339</ymin>
			<xmax>502</xmax>
			<ymax>398</ymax>
		</bndbox>
	</object>
	
    <object>
		<pose>Unspecified</pose>
		<truncated>0</truncated>
		<difficult>0</difficult>

		<name>echinus</name>
		<bndbox>
			<xmin>1395</xmin>
			<ymin>251</ymin>
			<xmax>1452</xmax>
			<ymax>300</ymax>
		</bndbox>
	</object>
	
    <object>
		<pose>Unspecified</pose>
		<truncated>0</truncated>
		<difficult>0</difficult>

		<name>echinus</name>
		<bndbox>
			<xmin>187</xmin>
			<ymin>544</ymin>
			<xmax>258</xmax>
			<ymax>605</ymax>
		</bndbox>
	</object>
	
    <object>
		<pose>Unspecified</pose>
		<truncated>0</truncated>
		<difficult>0</difficult>

		<name>echinus</name>
		<bndbox>
			<xmin>1115</xmin>
			<ymin>351</ymin>
			<xmax>1162</xmax>
			<ymax>393</ymax>
		</bndbox>
	</object>
	
    <object>
		<pose>Unspecified</pose>
		<truncated>0</truncated>
		<difficult>0</difficult>

		<name>echinus</name>
		<bndbox>
			<xmin>608</xmin>
			<ymin>246</ymin>
			<xmax>687</xmax>
			<ymax>321</ymax>
		</bndbox>
	</object>
	
    <object>
		<pose>Unspecified</pose>
		<truncated>0</truncated>
		<difficult>0</difficult>

		<name>echinus</name>
		<bndbox>
			<xmin>783</xmin>
			<ymin>151</ymin>
			<xmax>840</xmax>
			<ymax>203</ymax>
		</bndbox>
	</object>
	
    <object>
		<pose>Unspecified</pose>
		<truncated>0</truncated>
		<difficult>0</difficult>

		<name>echinus</name>
		<bndbox>
			<xmin>1081</xmin>
			<ymin>171</ymin>
			<xmax>1143</xmax>
			<ymax>223</ymax>
		</bndbox>
	</object>
	
    <object>
		<pose>Unspecified</pose>
		<truncated>0</truncated>
		<difficult>0</difficult>

		<name>echinus</name>
		<bndbox>
			<xmin>1271</xmin>
			<ymin>317</ymin>
			<xmax>1349</xmax>
			<ymax>380</ymax>
		</bndbox>
	</object>
	
    <object>
		<pose>Unspecified</pose>
		<truncated>0</truncated>
		<difficult>0</difficult>

		<name>starfish</name>
		<bndbox>
			<xmin>1232</xmin>
			<ymin>950</ymin>
			<xmax>1331</xmax>
			<ymax>1031</ymax>
		</bndbox>
	</object>
	
    <object>
		<pose>Unspecified</pose>
		<truncated>0</truncated>
		<difficult>0</difficult>

		<name>starfish</name>
		<bndbox>
			<xmin>619</xmin>
			<ymin>716</ymin>
			<xmax>687</xmax>
			<ymax>776</ymax>
		</bndbox>
	</object>
	
    <object>
		<pose>Unspecified</pose>
		<truncated>0</truncated>
		<difficult>0</difficult>

		<name>starfish</name>
		<bndbox>
			<xmin>79</xmin>
			<ymin>576</ymin>
			<xmax>202</xmax>
			<ymax>669</ymax>
		</bndbox>
	</object>
</annotation>
