<?xml version="1.0" encoding="utf-8"?>
<annotation>
	<folder>instances_train_xml</folder>
	<filename>513.jpg</filename>
	<size>
		<width>1920</width>
		<height>1080</height>
	</size>
	
    <object>
		<pose>Unspecified</pose>
		<truncated>0</truncated>
		<difficult>0</difficult>

		<name>echinus</name>
		<bndbox>
			<xmin>1190</xmin>
			<ymin>537</ymin>
			<xmax>1469</xmax>
			<ymax>767</ymax>
		</bndbox>
	</object>
	
    <object>
		<pose>Unspecified</pose>
		<truncated>0</truncated>
		<difficult>0</difficult>

		<name>starfish</name>
		<bndbox>
			<xmin>922</xmin>
			<ymin>528</ymin>
			<xmax>1146</xmax>
			<ymax>710</ymax>
		</bndbox>
	</object>
	
    <object>
		<pose>Unspecified</pose>
		<truncated>0</truncated>
		<difficult>0</difficult>

		<name>starfish</name>
		<bndbox>
			<xmin>642</xmin>
			<ymin>184</ymin>
			<xmax>822</xmax>
			<ymax>322</ymax>
		</bndbox>
	</object>
	
    <object>
		<pose>Unspecified</pose>
		<truncated>0</truncated>
		<difficult>0</difficult>

		<name>starfish</name>
		<bndbox>
			<xmin>872</xmin>
			<ymin>920</ymin>
			<xmax>1260</xmax>
			<ymax>1072</ymax>
		</bndbox>
	</object>
</annotation>
