<?xml version="1.0" encoding="utf-8"?>
<annotation>
	<folder>instances_train_xml</folder>
	<filename>528.jpg</filename>
	<size>
		<width>3840</width>
		<height>2160</height>
	</size>
	
    <object>
		<pose>Unspecified</pose>
		<truncated>0</truncated>
		<difficult>0</difficult>

		<name>echinus</name>
		<bndbox>
			<xmin>1493</xmin>
			<ymin>1985</ymin>
			<xmax>1638</xmax>
			<ymax>2152</ymax>
		</bndbox>
	</object>
	
    <object>
		<pose>Unspecified</pose>
		<truncated>0</truncated>
		<difficult>0</difficult>

		<name>echinus</name>
		<bndbox>
			<xmin>1182</xmin>
			<ymin>2025</ymin>
			<xmax>1425</xmax>
			<ymax>2161</ymax>
		</bndbox>
	</object>
	
    <object>
		<pose>Unspecified</pose>
		<truncated>0</truncated>
		<difficult>0</difficult>

		<name>echinus</name>
		<bndbox>
			<xmin>2134</xmin>
			<ymin>488</ymin>
			<xmax>2368</xmax>
			<ymax>694</ymax>
		</bndbox>
	</object>
	
    <object>
		<pose>Unspecified</pose>
		<truncated>0</truncated>
		<difficult>0</difficult>

		<name>echinus</name>
		<bndbox>
			<xmin>103</xmin>
			<ymin>1187</ymin>
			<xmax>465</xmax>
			<ymax>1382</ymax>
		</bndbox>
	</object>
	
    <object>
		<pose>Unspecified</pose>
		<truncated>0</truncated>
		<difficult>0</difficult>

		<name>echinus</name>
		<bndbox>
			<xmin>26</xmin>
			<ymin>1428</ymin>
			<xmax>334</xmax>
			<ymax>1627</ymax>
		</bndbox>
	</object>
</annotation>
