<?xml version="1.0" encoding="utf-8"?>
<annotation>
	<folder>instances_train_xml</folder>
	<filename>571.jpg</filename>
	<size>
		<width>720</width>
		<height>405</height>
	</size>
	
    <object>
		<pose>Unspecified</pose>
		<truncated>0</truncated>
		<difficult>0</difficult>

		<name>echinus</name>
		<bndbox>
			<xmin>234</xmin>
			<ymin>157</ymin>
			<xmax>320</xmax>
			<ymax>236</ymax>
		</bndbox>
	</object>
	
    <object>
		<pose>Unspecified</pose>
		<truncated>0</truncated>
		<difficult>0</difficult>

		<name>echinus</name>
		<bndbox>
			<xmin>379</xmin>
			<ymin>323</ymin>
			<xmax>446</xmax>
			<ymax>391</ymax>
		</bndbox>
	</object>
	
    <object>
		<pose>Unspecified</pose>
		<truncated>0</truncated>
		<difficult>0</difficult>

		<name>echinus</name>
		<bndbox>
			<xmin>475</xmin>
			<ymin>348</ymin>
			<xmax>519</xmax>
			<ymax>395</ymax>
		</bndbox>
	</object>
	
    <object>
		<pose>Unspecified</pose>
		<truncated>0</truncated>
		<difficult>0</difficult>

		<name>echinus</name>
		<bndbox>
			<xmin>425</xmin>
			<ymin>249</ymin>
			<xmax>457</xmax>
			<ymax>286</ymax>
		</bndbox>
	</object>
</annotation>
