<?xml version="1.0" encoding="utf-8"?>
<annotation>
	<folder>instances_train_xml</folder>
	<filename>6490.jpg</filename>
	<size>
		<width>720</width>
		<height>405</height>
	</size>
	
    <object>
		<pose>Unspecified</pose>
		<truncated>0</truncated>
		<difficult>0</difficult>

		<name>holothurian</name>
		<bndbox>
			<xmin>521</xmin>
			<ymin>218</ymin>
			<xmax>683</xmax>
			<ymax>370</ymax>
		</bndbox>
	</object>
	
    <object>
		<pose>Unspecified</pose>
		<truncated>0</truncated>
		<difficult>0</difficult>

		<name>holothurian</name>
		<bndbox>
			<xmin>408</xmin>
			<ymin>179</ymin>
			<xmax>564</xmax>
			<ymax>328</ymax>
		</bndbox>
	</object>
</annotation>
