<?xml version="1.0" encoding="utf-8"?>
<annotation>
	<folder>instances_train_xml</folder>
	<filename>6500.jpg</filename>
	<size>
		<width>3840</width>
		<height>2160</height>
	</size>
	
    <object>
		<pose>Unspecified</pose>
		<truncated>0</truncated>
		<difficult>0</difficult>

		<name>holothurian</name>
		<bndbox>
			<xmin>951</xmin>
			<ymin>784</ymin>
			<xmax>1080</xmax>
			<ymax>878</ymax>
		</bndbox>
	</object>
	
    <object>
		<pose>Unspecified</pose>
		<truncated>0</truncated>
		<difficult>0</difficult>

		<name>starfish</name>
		<bndbox>
			<xmin>1012</xmin>
			<ymin>662</ymin>
			<xmax>1125</xmax>
			<ymax>770</ymax>
		</bndbox>
	</object>
	
    <object>
		<pose>Unspecified</pose>
		<truncated>0</truncated>
		<difficult>0</difficult>

		<name>starfish</name>
		<bndbox>
			<xmin>1431</xmin>
			<ymin>551</ymin>
			<xmax>1507</xmax>
			<ymax>673</ymax>
		</bndbox>
	</object>
	
    <object>
		<pose>Unspecified</pose>
		<truncated>0</truncated>
		<difficult>0</difficult>

		<name>starfish</name>
		<bndbox>
			<xmin>2423</xmin>
			<ymin>842</ymin>
			<xmax>2655</xmax>
			<ymax>1069</ymax>
		</bndbox>
	</object>
	
    <object>
		<pose>Unspecified</pose>
		<truncated>0</truncated>
		<difficult>0</difficult>

		<name>starfish</name>
		<bndbox>
			<xmin>2883</xmin>
			<ymin>784</ymin>
			<xmax>2961</xmax>
			<ymax>922</ymax>
		</bndbox>
	</object>
	
    <object>
		<pose>Unspecified</pose>
		<truncated>0</truncated>
		<difficult>0</difficult>

		<name>holothurian</name>
		<bndbox>
			<xmin>3032</xmin>
			<ymin>2097</ymin>
			<xmax>3157</xmax>
			<ymax>2161</ymax>
		</bndbox>
	</object>
</annotation>
