<?xml version="1.0" encoding="utf-8"?>
<annotation>
	<folder>instances_test_xml</folder>
	<filename>355.jpg</filename>
	<size>
		<width>3840</width>
		<height>2160</height>
	</size>
	
    <object>
		<pose>Unspecified</pose>
		<truncated>0</truncated>
		<difficult>0</difficult>

		<name>holothurian</name>
		<bndbox>
			<xmin>1660</xmin>
			<ymin>25</ymin>
			<xmax>1860</xmax>
			<ymax>282</ymax>
		</bndbox>
	</object>
	
    <object>
		<pose>Unspecified</pose>
		<truncated>0</truncated>
		<difficult>0</difficult>

		<name>starfish</name>
		<bndbox>
			<xmin>2475</xmin>
			<ymin>85</ymin>
			<xmax>2802</xmax>
			<ymax>245</ymax>
		</bndbox>
	</object>
	
    <object>
		<pose>Unspecified</pose>
		<truncated>0</truncated>
		<difficult>0</difficult>

		<name>scallop</name>
		<bndbox>
			<xmin>2407</xmin>
			<ymin>318</ymin>
			<xmax>2702</xmax>
			<ymax>509</ymax>
		</bndbox>
	</object>
	
    <object>
		<pose>Unspecified</pose>
		<truncated>0</truncated>
		<difficult>0</difficult>

		<name>scallop</name>
		<bndbox>
			<xmin>2883</xmin>
			<ymin>404</ymin>
			<xmax>3464</xmax>
			<ymax>734</ymax>
		</bndbox>
	</object>
	
    <object>
		<pose>Unspecified</pose>
		<truncated>0</truncated>
		<difficult>0</difficult>

		<name>scallop</name>
		<bndbox>
			<xmin>3005</xmin>
			<ymin>1020</ymin>
			<xmax>3623</xmax>
			<ymax>1366</ymax>
		</bndbox>
	</object>
	
    <object>
		<pose>Unspecified</pose>
		<truncated>0</truncated>
		<difficult>0</difficult>

		<name>scallop</name>
		<bndbox>
			<xmin>2578</xmin>
			<ymin>1515</ymin>
			<xmax>3259</xmax>
			<ymax>1926</ymax>
		</bndbox>
	</object>
	
    <object>
		<pose>Unspecified</pose>
		<truncated>0</truncated>
		<difficult>0</difficult>

		<name>starfish</name>
		<bndbox>
			<xmin>1124</xmin>
			<ymin>364</ymin>
			<xmax>1335</xmax>
			<ymax>512</ymax>
		</bndbox>
	</object>
</annotation>
