<?xml version="1.0" encoding="utf-8"?>
<annotation>
	<folder>instances_test_xml</folder>
	<filename>46.jpg</filename>
	<size>
		<width>3840</width>
		<height>2160</height>
	</size>
	
    <object>
		<pose>Unspecified</pose>
		<truncated>0</truncated>
		<difficult>0</difficult>

		<name>holothurian</name>
		<bndbox>
			<xmin>67</xmin>
			<ymin>1123</ymin>
			<xmax>726</xmax>
			<ymax>1631</ymax>
		</bndbox>
	</object>
	
    <object>
		<pose>Unspecified</pose>
		<truncated>0</truncated>
		<difficult>0</difficult>

		<name>echinus</name>
		<bndbox>
			<xmin>760</xmin>
			<ymin>835</ymin>
			<xmax>1102</xmax>
			<ymax>1069</ymax>
		</bndbox>
	</object>
	
    <object>
		<pose>Unspecified</pose>
		<truncated>0</truncated>
		<difficult>0</difficult>

		<name>echinus</name>
		<bndbox>
			<xmin>1885</xmin>
			<ymin>853</ymin>
			<xmax>2097</xmax>
			<ymax>1025</ymax>
		</bndbox>
	</object>
	
    <object>
		<pose>Unspecified</pose>
		<truncated>0</truncated>
		<difficult>0</difficult>

		<name>echinus</name>
		<bndbox>
			<xmin>2844</xmin>
			<ymin>1070</ymin>
			<xmax>2970</xmax>
			<ymax>1180</ymax>
		</bndbox>
	</object>
	
    <object>
		<pose>Unspecified</pose>
		<truncated>0</truncated>
		<difficult>0</difficult>

		<name>echinus</name>
		<bndbox>
			<xmin>2612</xmin>
			<ymin>979</ymin>
			<xmax>2707</xmax>
			<ymax>1068</ymax>
		</bndbox>
	</object>
	
    <object>
		<pose>Unspecified</pose>
		<truncated>0</truncated>
		<difficult>0</difficult>

		<name>echinus</name>
		<bndbox>
			<xmin>1289</xmin>
			<ymin>723</ymin>
			<xmax>1370</xmax>
			<ymax>778</ymax>
		</bndbox>
	</object>
	
    <object>
		<pose>Unspecified</pose>
		<truncated>0</truncated>
		<difficult>0</difficult>

		<name>echinus</name>
		<bndbox>
			<xmin>2901</xmin>
			<ymin>796</ymin>
			<xmax>3003</xmax>
			<ymax>891</ymax>
		</bndbox>
	</object>
	
    <object>
		<pose>Unspecified</pose>
		<truncated>0</truncated>
		<difficult>0</difficult>

		<name>echinus</name>
		<bndbox>
			<xmin>220</xmin>
			<ymin>763</ymin>
			<xmax>368</xmax>
			<ymax>873</ymax>
		</bndbox>
	</object>
	
    <object>
		<pose>Unspecified</pose>
		<truncated>0</truncated>
		<difficult>0</difficult>

		<name>echinus</name>
		<bndbox>
			<xmin>1833</xmin>
			<ymin>762</ymin>
			<xmax>1944</xmax>
			<ymax>854</ymax>
		</bndbox>
	</object>
	
    <object>
		<pose>Unspecified</pose>
		<truncated>0</truncated>
		<difficult>0</difficult>

		<name>echinus</name>
		<bndbox>
			<xmin>2215</xmin>
			<ymin>886</ymin>
			<xmax>2310</xmax>
			<ymax>963</ymax>
		</bndbox>
	</object>
	
    <object>
		<pose>Unspecified</pose>
		<truncated>0</truncated>
		<difficult>0</difficult>

		<name>echinus</name>
		<bndbox>
			<xmin>1581</xmin>
			<ymin>683</ymin>
			<xmax>1667</xmax>
			<ymax>748</ymax>
		</bndbox>
	</object>
	
    <object>
		<pose>Unspecified</pose>
		<truncated>0</truncated>
		<difficult>0</difficult>

		<name>echinus</name>
		<bndbox>
			<xmin>1577</xmin>
			<ymin>595</ymin>
			<xmax>1656</xmax>
			<ymax>660</ymax>
		</bndbox>
	</object>
	
    <object>
		<pose>Unspecified</pose>
		<truncated>0</truncated>
		<difficult>0</difficult>

		<name>starfish</name>
		<bndbox>
			<xmin>968</xmin>
			<ymin>1041</ymin>
			<xmax>1297</xmax>
			<ymax>1263</ymax>
		</bndbox>
	</object>
	
    <object>
		<pose>Unspecified</pose>
		<truncated>0</truncated>
		<difficult>0</difficult>

		<name>starfish</name>
		<bndbox>
			<xmin>1815</xmin>
			<ymin>823</ymin>
			<xmax>1939</xmax>
			<ymax>896</ymax>
		</bndbox>
	</object>
	
    <object>
		<pose>Unspecified</pose>
		<truncated>0</truncated>
		<difficult>0</difficult>

		<name>echinus</name>
		<bndbox>
			<xmin>1246</xmin>
			<ymin>694</ymin>
			<xmax>1327</xmax>
			<ymax>749</ymax>
		</bndbox>
	</object>
	
    <object>
		<pose>Unspecified</pose>
		<truncated>0</truncated>
		<difficult>0</difficult>

		<name>echinus</name>
		<bndbox>
			<xmin>1307</xmin>
			<ymin>687</ymin>
			<xmax>1388</xmax>
			<ymax>742</ymax>
		</bndbox>
	</object>
	
    <object>
		<pose>Unspecified</pose>
		<truncated>0</truncated>
		<difficult>0</difficult>

		<name>echinus</name>
		<bndbox>
			<xmin>1363</xmin>
			<ymin>677</ymin>
			<xmax>1460</xmax>
			<ymax>743</ymax>
		</bndbox>
	</object>
	
    <object>
		<pose>Unspecified</pose>
		<truncated>0</truncated>
		<difficult>0</difficult>

		<name>echinus</name>
		<bndbox>
			<xmin>2334</xmin>
			<ymin>921</ymin>
			<xmax>2436</xmax>
			<ymax>1016</ymax>
		</bndbox>
	</object>
	
    <object>
		<pose>Unspecified</pose>
		<truncated>0</truncated>
		<difficult>0</difficult>

		<name>echinus</name>
		<bndbox>
			<xmin>1928</xmin>
			<ymin>726</ymin>
			<xmax>2009</xmax>
			<ymax>790</ymax>
		</bndbox>
	</object>
	
    <object>
		<pose>Unspecified</pose>
		<truncated>0</truncated>
		<difficult>0</difficult>

		<name>echinus</name>
		<bndbox>
			<xmin>2138</xmin>
			<ymin>688</ymin>
			<xmax>2219</xmax>
			<ymax>752</ymax>
		</bndbox>
	</object>
	
    <object>
		<pose>Unspecified</pose>
		<truncated>0</truncated>
		<difficult>0</difficult>

		<name>echinus</name>
		<bndbox>
			<xmin>2215</xmin>
			<ymin>744</ymin>
			<xmax>2296</xmax>
			<ymax>808</ymax>
		</bndbox>
	</object>
	
    <object>
		<pose>Unspecified</pose>
		<truncated>0</truncated>
		<difficult>0</difficult>

		<name>echinus</name>
		<bndbox>
			<xmin>2204</xmin>
			<ymin>590</ymin>
			<xmax>2285</xmax>
			<ymax>654</ymax>
		</bndbox>
	</object>
	
    <object>
		<pose>Unspecified</pose>
		<truncated>0</truncated>
		<difficult>0</difficult>

		<name>echinus</name>
		<bndbox>
			<xmin>2305</xmin>
			<ymin>698</ymin>
			<xmax>2386</xmax>
			<ymax>762</ymax>
		</bndbox>
	</object>
	
    <object>
		<pose>Unspecified</pose>
		<truncated>0</truncated>
		<difficult>0</difficult>

		<name>echinus</name>
		<bndbox>
			<xmin>2305</xmin>
			<ymin>605</ymin>
			<xmax>2386</xmax>
			<ymax>669</ymax>
		</bndbox>
	</object>
	
    <object>
		<pose>Unspecified</pose>
		<truncated>0</truncated>
		<difficult>0</difficult>

		<name>echinus</name>
		<bndbox>
			<xmin>2418</xmin>
			<ymin>664</ymin>
			<xmax>2499</xmax>
			<ymax>728</ymax>
		</bndbox>
	</object>
	
    <object>
		<pose>Unspecified</pose>
		<truncated>0</truncated>
		<difficult>0</difficult>

		<name>echinus</name>
		<bndbox>
			<xmin>2546</xmin>
			<ymin>655</ymin>
			<xmax>2627</xmax>
			<ymax>719</ymax>
		</bndbox>
	</object>
	
    <object>
		<pose>Unspecified</pose>
		<truncated>0</truncated>
		<difficult>0</difficult>

		<name>echinus</name>
		<bndbox>
			<xmin>2661</xmin>
			<ymin>663</ymin>
			<xmax>2742</xmax>
			<ymax>727</ymax>
		</bndbox>
	</object>
	
    <object>
		<pose>Unspecified</pose>
		<truncated>0</truncated>
		<difficult>0</difficult>

		<name>echinus</name>
		<bndbox>
			<xmin>2763</xmin>
			<ymin>555</ymin>
			<xmax>2821</xmax>
			<ymax>610</ymax>
		</bndbox>
	</object>
	
    <object>
		<pose>Unspecified</pose>
		<truncated>0</truncated>
		<difficult>0</difficult>

		<name>echinus</name>
		<bndbox>
			<xmin>2813</xmin>
			<ymin>610</ymin>
			<xmax>2871</xmax>
			<ymax>665</ymax>
		</bndbox>
	</object>
	
    <object>
		<pose>Unspecified</pose>
		<truncated>0</truncated>
		<difficult>0</difficult>

		<name>echinus</name>
		<bndbox>
			<xmin>3076</xmin>
			<ymin>713</ymin>
			<xmax>3134</xmax>
			<ymax>768</ymax>
		</bndbox>
	</object>
	
    <object>
		<pose>Unspecified</pose>
		<truncated>0</truncated>
		<difficult>0</difficult>

		<name>echinus</name>
		<bndbox>
			<xmin>3078</xmin>
			<ymin>671</ymin>
			<xmax>3136</xmax>
			<ymax>726</ymax>
		</bndbox>
	</object>
	
    <object>
		<pose>Unspecified</pose>
		<truncated>0</truncated>
		<difficult>0</difficult>

		<name>echinus</name>
		<bndbox>
			<xmin>2945</xmin>
			<ymin>1030</ymin>
			<xmax>3003</xmax>
			<ymax>1085</ymax>
		</bndbox>
	</object>
</annotation>
